quantminer/__init__.py
quantminer/classes/__init__.py
quantminer/classes/reducers.py
quantminer/classes/seqkmeans.py
quantminer/data/data.py
quantminer/pipminer.pkl
quantminer/pipminer.py
quantminer-2.0.0.dist-info/METADATA
quantminer-2.0.0.dist-info/WHEEL
quantminer-2.0.0.dist-info/RECORD
